ontouml_vocabulary_lib/__init__.py
ontouml_vocabulary_lib/constants/__init__.py
ontouml_vocabulary_lib/constants/constants_classes.py
ontouml_vocabulary_lib/constants/constants_misc.py
ontouml_vocabulary_lib/exceptions.py
ontouml_vocabulary_lib/terms.py
ontouml_vocabulary_lib-1.0.1.dist-info/LICENSE
ontouml_vocabulary_lib-1.0.1.dist-info/METADATA
ontouml_vocabulary_lib-1.0.1.dist-info/WHEEL
ontouml_vocabulary_lib-1.0.1.dist-info/RECORD
