Metadata-Version: 2.1
Name: ontouml_vocabulary_lib
Version: 1.0.1
Summary: OntoUML Python Library
Home-page: https://w3id.org/ontouml/vocabulary-lib
License: Apache-2.0
Keywords: semantic-web,knowledge-graph,ontouml,ontology-driven-development,ontouml-vocabulary,rdflib
Author: Pedro Paulo F. Barcelos
Author-email: p.p.favatobarcelos@utwente.nl
Requires-Python: >=3.09,<4.0
Classifier: License :: OSI Approved :: Apache Software License
Classifier: Programming Language :: Python :: 3
Classifier: Programming Language :: Python :: 3.9
Classifier: Programming Language :: Python :: 3.10
Classifier: Programming Language :: Python :: 3.11
Requires-Dist: rdflib (>=7.0.0,<8.0.0)
Project-URL: Documentation, https://w3id.org/ontouml/vocabulary-lib/docs
Project-URL: PyPi Project, https://pypi.org/project/ontouml-vocabulary-lib/
Project-URL: Repository, https://w3id.org/ontouml/vocabulary-lib
